TaileLantu/README.md
TaileLantu/__init__.py
TaileLantu/__main__.py
TaileLantu/file.epub
TaileLantu/index.html
TaileLantu/css/__init__.py
TaileLantu/css/annotations.css
TaileLantu/css/main.css
TaileLantu/css/normalize.css
TaileLantu/css/popup.css
TaileLantu/font/__init__.py
TaileLantu/font/fontello.eot
TaileLantu/font/fontello.svg
TaileLantu/font/fontello.ttf
TaileLantu/font/fontello.woff
TaileLantu/img/__init__.py
TaileLantu/img/annotator-glyph-sprite.png
TaileLantu/img/annotator-icon-sprite.png
TaileLantu/img/apple-touch-icon.png
TaileLantu/img/cancelfullscreen.png
TaileLantu/img/close.png
TaileLantu/img/fullscreen.png
TaileLantu/img/loader.gif
TaileLantu/img/menu-icon.png
TaileLantu/img/save.png
TaileLantu/img/saved.png
TaileLantu/img/settings-s.png
TaileLantu/img/settings.png
TaileLantu/img/star.png
TaileLantu/js/__init__.py
TaileLantu/js/epub.js
TaileLantu/js/epub.min.js
TaileLantu/js/epub.min.map
TaileLantu/js/hooks.min.js
TaileLantu/js/hooks.min.map
TaileLantu/js/reader.js
TaileLantu/js/reader.js.map
TaileLantu/js/reader.min.js
TaileLantu/js/reader.min.map
TaileLantu/js/hooks/__init__.py
TaileLantu/js/hooks/extensions/__init__.py
TaileLantu/js/hooks/extensions/highlight.js
TaileLantu/js/libs/__init__.py
TaileLantu/js/libs/jquery.min.js
TaileLantu/js/libs/localforage.min.js
TaileLantu/js/libs/screenfull.js
TaileLantu/js/libs/screenfull.min.js
TaileLantu/js/libs/zip.min.js
TaileLantu/js/plugins/__init__.py
TaileLantu/js/plugins/hypothesis.js
TaileLantu/js/plugins/search.js
taile_lantu-2022.10.11.0.dist-info/METADATA
taile_lantu-2022.10.11.0.dist-info/WHEEL
taile_lantu-2022.10.11.0.dist-info/entry_points.txt
taile_lantu-2022.10.11.0.dist-info/top_level.txt
taile_lantu-2022.10.11.0.dist-info/RECORD
